{"nodes": [{"id": "e_website_stock_analysis_stock_ticker_v2_backend_vendor_scrapling_tests_fetchers_test_response_handling_py", "label": "test_response_handling.py", "file_type": "code", "source_file": "E:\\Website\\Stock Analysis\\stock ticker v2\\backend\\vendor\\scrapling\\tests\\fetchers\\test_response_handling.py", "source_location": "L1"}, {"id": "test_response_handling_testresponsefactory", "label": "TestResponseFactory", "file_type": "code", "source_file": "E:\\Website\\Stock Analysis\\stock ticker v2\\backend\\vendor\\scrapling\\tests\\fetchers\\test_response_handling.py", "source_location": "L7"}, {"id": "test_response_handling_testresponsefactory_test_response_from_curl", "label": ".test_response_from_curl()", "file_type": "code", "source_file": "E:\\Website\\Stock Analysis\\stock ticker v2\\backend\\vendor\\scrapling\\tests\\fetchers\\test_response_handling.py", "source_location": "L10"}, {"id": "test_response_handling_testresponsefactory_test_response_history_processing", "label": ".test_response_history_processing()", "file_type": "code", "source_file": "E:\\Website\\Stock Analysis\\stock ticker v2\\backend\\vendor\\scrapling\\tests\\fetchers\\test_response_handling.py", "source_location": "L34"}, {"id": "test_response_handling_testerrorscenarios", "label": "TestErrorScenarios", "file_type": "code", "source_file": "E:\\Website\\Stock Analysis\\stock ticker v2\\backend\\vendor\\scrapling\\tests\\fetchers\\test_response_handling.py", "source_location": "L60"}, {"id": "test_response_handling_testerrorscenarios_test_invalid_html_handling", "label": ".test_invalid_html_handling()", "file_type": "code", "source_file": "E:\\Website\\Stock Analysis\\stock ticker v2\\backend\\vendor\\scrapling\\tests\\fetchers\\test_response_handling.py", "source_location": "L63"}, {"id": "test_response_handling_testerrorscenarios_test_empty_responses", "label": ".test_empty_responses()", "file_type": "code", "source_file": "E:\\Website\\Stock Analysis\\stock ticker v2\\backend\\vendor\\scrapling\\tests\\fetchers\\test_response_handling.py", "source_location": "L82"}, {"id": "test_response_handling_rationale_8", "label": "Test ResponseFactory functionality", "file_type": "rationale", "source_file": "E:\\Website\\Stock Analysis\\stock ticker v2\\backend\\vendor\\scrapling\\tests\\fetchers\\test_response_handling.py", "source_location": "L8"}, {"id": "test_response_handling_rationale_11", "label": "Test creating response from curl_cffi response", "file_type": "rationale", "source_file": "E:\\Website\\Stock Analysis\\stock ticker v2\\backend\\vendor\\scrapling\\tests\\fetchers\\test_response_handling.py", "source_location": "L11"}, {"id": "test_response_handling_rationale_35", "label": "Test processing response history", "file_type": "rationale", "source_file": "E:\\Website\\Stock Analysis\\stock ticker v2\\backend\\vendor\\scrapling\\tests\\fetchers\\test_response_handling.py", "source_location": "L35"}, {"id": "test_response_handling_rationale_61", "label": "Test various error scenarios", "file_type": "rationale", "source_file": "E:\\Website\\Stock Analysis\\stock ticker v2\\backend\\vendor\\scrapling\\tests\\fetchers\\test_response_handling.py", "source_location": "L61"}, {"id": "test_response_handling_rationale_64", "label": "Test handling of malformed HTML", "file_type": "rationale", "source_file": "E:\\Website\\Stock Analysis\\stock ticker v2\\backend\\vendor\\scrapling\\tests\\fetchers\\test_response_handling.py", "source_location": "L64"}, {"id": "test_response_handling_rationale_83", "label": "Test handling of empty responses", "file_type": "rationale", "source_file": "E:\\Website\\Stock Analysis\\stock ticker v2\\backend\\vendor\\scrapling\\tests\\fetchers\\test_response_handling.py", "source_location": "L83"}], "edges": [{"source": "e_website_stock_analysis_stock_ticker_v2_backend_vendor_scrapling_tests_fetchers_test_response_handling_py", "target": "unittest_mock", "relation": "imports_from", "confidence": "EXTRACTED", "source_file": "E:\\Website\\Stock Analysis\\stock ticker v2\\backend\\vendor\\scrapling\\tests\\fetchers\\test_response_handling.py", "source_location": "L1", "weight": 1.0}, {"source": "e_website_stock_analysis_stock_ticker_v2_backend_vendor_scrapling_tests_fetchers_test_response_handling_py", "target": "scrapling_parser", "relation": "imports_from", "confidence": "EXTRACTED", "source_file": "E:\\Website\\Stock Analysis\\stock ticker v2\\backend\\vendor\\scrapling\\tests\\fetchers\\test_response_handling.py", "source_location": "L3", "weight": 1.0}, {"source": "e_website_stock_analysis_stock_ticker_v2_backend_vendor_scrapling_tests_fetchers_test_response_handling_py", "target": "scrapling_engines_toolbelt_convertor", "relation": "imports_from", "confidence": "EXTRACTED", "source_file": "E:\\Website\\Stock Analysis\\stock ticker v2\\backend\\vendor\\scrapling\\tests\\fetchers\\test_response_handling.py", "source_location": "L4", "weight": 1.0}, {"source": "e_website_stock_analysis_stock_ticker_v2_backend_vendor_scrapling_tests_fetchers_test_response_handling_py", "target": "test_response_handling_testresponsefactory", "relation": "contains", "confidence": "EXTRACTED", "source_file": "E:\\Website\\Stock Analysis\\stock ticker v2\\backend\\vendor\\scrapling\\tests\\fetchers\\test_response_handling.py", "source_location": "L7", "weight": 1.0}, {"source": "test_response_handling_testresponsefactory", "target": "test_response_handling_testresponsefactory_test_response_from_curl", "relation": "method", "confidence": "EXTRACTED", "source_file": "E:\\Website\\Stock Analysis\\stock ticker v2\\backend\\vendor\\scrapling\\tests\\fetchers\\test_response_handling.py", "source_location": "L10", "weight": 1.0}, {"source": "test_response_handling_testresponsefactory", "target": "test_response_handling_testresponsefactory_test_response_history_processing", "relation": "method", "confidence": "EXTRACTED", "source_file": "E:\\Website\\Stock Analysis\\stock ticker v2\\backend\\vendor\\scrapling\\tests\\fetchers\\test_response_handling.py", "source_location": "L34", "weight": 1.0}, {"source": "e_website_stock_analysis_stock_ticker_v2_backend_vendor_scrapling_tests_fetchers_test_response_handling_py", "target": "test_response_handling_testerrorscenarios", "relation": "contains", "confidence": "EXTRACTED", "source_file": "E:\\Website\\Stock Analysis\\stock ticker v2\\backend\\vendor\\scrapling\\tests\\fetchers\\test_response_handling.py", "source_location": "L60", "weight": 1.0}, {"source": "test_response_handling_testerrorscenarios", "target": "test_response_handling_testerrorscenarios_test_invalid_html_handling", "relation": "method", "confidence": "EXTRACTED", "source_file": "E:\\Website\\Stock Analysis\\stock ticker v2\\backend\\vendor\\scrapling\\tests\\fetchers\\test_response_handling.py", "source_location": "L63", "weight": 1.0}, {"source": "test_response_handling_testerrorscenarios", "target": "test_response_handling_testerrorscenarios_test_empty_responses", "relation": "method", "confidence": "EXTRACTED", "source_file": "E:\\Website\\Stock Analysis\\stock ticker v2\\backend\\vendor\\scrapling\\tests\\fetchers\\test_response_handling.py", "source_location": "L82", "weight": 1.0}, {"source": "test_response_handling_rationale_8", "target": "test_response_handling_testresponsefactory", "relation": "rationale_for", "confidence": "EXTRACTED", "source_file": "E:\\Website\\Stock Analysis\\stock ticker v2\\backend\\vendor\\scrapling\\tests\\fetchers\\test_response_handling.py", "source_location": "L8", "weight": 1.0}, {"source": "test_response_handling_rationale_11", "target": "test_response_handling_testresponsefactory_test_response_from_curl", "relation": "rationale_for", "confidence": "EXTRACTED", "source_file": "E:\\Website\\Stock Analysis\\stock ticker v2\\backend\\vendor\\scrapling\\tests\\fetchers\\test_response_handling.py", "source_location": "L11", "weight": 1.0}, {"source": "test_response_handling_rationale_35", "target": "test_response_handling_testresponsefactory_test_response_history_processing", "relation": "rationale_for", "confidence": "EXTRACTED", "source_file": "E:\\Website\\Stock Analysis\\stock ticker v2\\backend\\vendor\\scrapling\\tests\\fetchers\\test_response_handling.py", "source_location": "L35", "weight": 1.0}, {"source": "test_response_handling_rationale_61", "target": "test_response_handling_testerrorscenarios", "relation": "rationale_for", "confidence": "EXTRACTED", "source_file": "E:\\Website\\Stock Analysis\\stock ticker v2\\backend\\vendor\\scrapling\\tests\\fetchers\\test_response_handling.py", "source_location": "L61", "weight": 1.0}, {"source": "test_response_handling_rationale_64", "target": "test_response_handling_testerrorscenarios_test_invalid_html_handling", "relation": "rationale_for", "confidence": "EXTRACTED", "source_file": "E:\\Website\\Stock Analysis\\stock ticker v2\\backend\\vendor\\scrapling\\tests\\fetchers\\test_response_handling.py", "source_location": "L64", "weight": 1.0}, {"source": "test_response_handling_rationale_83", "target": "test_response_handling_testerrorscenarios_test_empty_responses", "relation": "rationale_for", "confidence": "EXTRACTED", "source_file": "E:\\Website\\Stock Analysis\\stock ticker v2\\backend\\vendor\\scrapling\\tests\\fetchers\\test_response_handling.py", "source_location": "L83", "weight": 1.0}], "raw_calls": [{"caller_nid": "test_response_handling_testresponsefactory_test_response_from_curl", "callee": "Mock", "source_file": "E:\\Website\\Stock Analysis\\stock ticker v2\\backend\\vendor\\scrapling\\tests\\fetchers\\test_response_handling.py", "source_location": "L13"}, {"caller_nid": "test_response_handling_testresponsefactory_test_response_from_curl", "callee": "from_http_request", "source_file": "E:\\Website\\Stock Analysis\\stock ticker v2\\backend\\vendor\\scrapling\\tests\\fetchers\\test_response_handling.py", "source_location": "L25"}, {"caller_nid": "test_response_handling_testresponsefactory_test_response_from_curl", "callee": "isinstance", "source_file": "E:\\Website\\Stock Analysis\\stock ticker v2\\backend\\vendor\\scrapling\\tests\\fetchers\\test_response_handling.py", "source_location": "L32"}, {"caller_nid": "test_response_handling_testresponsefactory_test_response_history_processing", "callee": "Mock", "source_file": "E:\\Website\\Stock Analysis\\stock ticker v2\\backend\\vendor\\scrapling\\tests\\fetchers\\test_response_handling.py", "source_location": "L37"}, {"caller_nid": "test_response_handling_testresponsefactory_test_response_history_processing", "callee": "Mock", "source_file": "E:\\Website\\Stock Analysis\\stock ticker v2\\backend\\vendor\\scrapling\\tests\\fetchers\\test_response_handling.py", "source_location": "L40"}, {"caller_nid": "test_response_handling_testresponsefactory_test_response_history_processing", "callee": "Mock", "source_file": "E:\\Website\\Stock Analysis\\stock ticker v2\\backend\\vendor\\scrapling\\tests\\fetchers\\test_response_handling.py", "source_location": "L42"}, {"caller_nid": "test_response_handling_testresponsefactory_test_response_history_processing", "callee": "Mock", "source_file": "E:\\Website\\Stock Analysis\\stock ticker v2\\backend\\vendor\\scrapling\\tests\\fetchers\\test_response_handling.py", "source_location": "L44"}, {"caller_nid": "test_response_handling_testresponsefactory_test_response_history_processing", "callee": "Mock", "source_file": "E:\\Website\\Stock Analysis\\stock ticker v2\\backend\\vendor\\scrapling\\tests\\fetchers\\test_response_handling.py", "source_location": "L45"}, {"caller_nid": "test_response_handling_testresponsefactory_test_response_history_processing", "callee": "Mock", "source_file": "E:\\Website\\Stock Analysis\\stock ticker v2\\backend\\vendor\\scrapling\\tests\\fetchers\\test_response_handling.py", "source_location": "L48"}, {"caller_nid": "test_response_handling_testresponsefactory_test_response_history_processing", "callee": "_process_response_history", "source_file": "E:\\Website\\Stock Analysis\\stock ticker v2\\backend\\vendor\\scrapling\\tests\\fetchers\\test_response_handling.py", "source_location": "L52"}, {"caller_nid": "test_response_handling_testresponsefactory_test_response_history_processing", "callee": "len", "source_file": "E:\\Website\\Stock Analysis\\stock ticker v2\\backend\\vendor\\scrapling\\tests\\fetchers\\test_response_handling.py", "source_location": "L57"}, {"caller_nid": "test_response_handling_testerrorscenarios_test_invalid_html_handling", "callee": "Selector", "source_file": "E:\\Website\\Stock Analysis\\stock ticker v2\\backend\\vendor\\scrapling\\tests\\fetchers\\test_response_handling.py", "source_location": "L75"}, {"caller_nid": "test_response_handling_testerrorscenarios_test_invalid_html_handling", "callee": "css", "source_file": "E:\\Website\\Stock Analysis\\stock ticker v2\\backend\\vendor\\scrapling\\tests\\fetchers\\test_response_handling.py", "source_location": "L79"}, {"caller_nid": "test_response_handling_testerrorscenarios_test_invalid_html_handling", "callee": "len", "source_file": "E:\\Website\\Stock Analysis\\stock ticker v2\\backend\\vendor\\scrapling\\tests\\fetchers\\test_response_handling.py", "source_location": "L80"}, {"caller_nid": "test_response_handling_testerrorscenarios_test_empty_responses", "callee": "Selector", "source_file": "E:\\Website\\Stock Analysis\\stock ticker v2\\backend\\vendor\\scrapling\\tests\\fetchers\\test_response_handling.py", "source_location": "L85"}, {"caller_nid": "test_response_handling_testerrorscenarios_test_empty_responses", "callee": "Selector", "source_file": "E:\\Website\\Stock Analysis\\stock ticker v2\\backend\\vendor\\scrapling\\tests\\fetchers\\test_response_handling.py", "source_location": "L89"}, {"caller_nid": "test_response_handling_testerrorscenarios_test_empty_responses", "callee": "Selector", "source_file": "E:\\Website\\Stock Analysis\\stock ticker v2\\backend\\vendor\\scrapling\\tests\\fetchers\\test_response_handling.py", "source_location": "L93"}, {"caller_nid": "test_response_handling_testerrorscenarios_test_empty_responses", "callee": "get_all_text", "source_file": "E:\\Website\\Stock Analysis\\stock ticker v2\\backend\\vendor\\scrapling\\tests\\fetchers\\test_response_handling.py", "source_location": "L94"}]}