{"nodes": [{"id": "e_website_stock_analysis_stock_ticker_v2_frontend_src_components_selflearninglab_jsx", "label": "SelfLearningLab.jsx", "file_type": "code", "source_file": "E:\\Website\\Stock Analysis\\stock ticker v2\\frontend\\src\\components\\SelfLearningLab.jsx", "source_location": "L1"}, {"id": "selflearninglab_fmtsigned", "label": "fmtSigned()", "file_type": "code", "source_file": "E:\\Website\\Stock Analysis\\stock ticker v2\\frontend\\src\\components\\SelfLearningLab.jsx", "source_location": "L20"}, {"id": "selflearninglab_selflearninglab", "label": "SelfLearningLab()", "file_type": "code", "source_file": "E:\\Website\\Stock Analysis\\stock ticker v2\\frontend\\src\\components\\SelfLearningLab.jsx", "source_location": "L26"}], "edges": [{"source": "e_website_stock_analysis_stock_ticker_v2_frontend_src_components_selflearninglab_jsx", "target": "react", "relation": "imports_from", "confidence": "EXTRACTED", "source_file": "E:\\Website\\Stock Analysis\\stock ticker v2\\frontend\\src\\components\\SelfLearningLab.jsx", "source_location": "L1", "weight": 1.0}, {"source": "e_website_stock_analysis_stock_ticker_v2_frontend_src_components_selflearninglab_jsx", "target": "e_website_stock_analysis_stock_ticker_v2_frontend_src_lib_api", "relation": "imports_from", "confidence": "EXTRACTED", "source_file": "E:\\Website\\Stock Analysis\\stock ticker v2\\frontend\\src\\components\\SelfLearningLab.jsx", "source_location": "L2", "weight": 1.0}, {"source": "e_website_stock_analysis_stock_ticker_v2_frontend_src_components_selflearninglab_jsx", "target": "lucide_react", "relation": "imports_from", "confidence": "EXTRACTED", "source_file": "E:\\Website\\Stock Analysis\\stock ticker v2\\frontend\\src\\components\\SelfLearningLab.jsx", "source_location": "L3", "weight": 1.0}, {"source": "e_website_stock_analysis_stock_ticker_v2_frontend_src_components_selflearninglab_jsx", "target": "selflearninglab_fmtsigned", "relation": "contains", "confidence": "EXTRACTED", "source_file": "E:\\Website\\Stock Analysis\\stock ticker v2\\frontend\\src\\components\\SelfLearningLab.jsx", "source_location": "L20", "weight": 1.0}, {"source": "e_website_stock_analysis_stock_ticker_v2_frontend_src_components_selflearninglab_jsx", "target": "selflearninglab_selflearninglab", "relation": "contains", "confidence": "EXTRACTED", "source_file": "E:\\Website\\Stock Analysis\\stock ticker v2\\frontend\\src\\components\\SelfLearningLab.jsx", "source_location": "L26", "weight": 1.0}, {"source": "selflearninglab_selflearninglab", "target": "selflearninglab_fmtsigned", "relation": "calls", "confidence": "EXTRACTED", "source_file": "E:\\Website\\Stock Analysis\\stock ticker v2\\frontend\\src\\components\\SelfLearningLab.jsx", "source_location": "L172", "weight": 1.0}], "raw_calls": [{"caller_nid": "selflearninglab_fmtsigned", "callee": "Number", "source_file": "E:\\Website\\Stock Analysis\\stock ticker v2\\frontend\\src\\components\\SelfLearningLab.jsx", "source_location": "L22"}, {"caller_nid": "selflearninglab_fmtsigned", "callee": "toFixed", "source_file": "E:\\Website\\Stock Analysis\\stock ticker v2\\frontend\\src\\components\\SelfLearningLab.jsx", "source_location": "L23"}, {"caller_nid": "selflearninglab_selflearninglab", "callee": "useState", "source_file": "E:\\Website\\Stock Analysis\\stock ticker v2\\frontend\\src\\components\\SelfLearningLab.jsx", "source_location": "L27"}, {"caller_nid": "selflearninglab_selflearninglab", "callee": "useState", "source_file": "E:\\Website\\Stock Analysis\\stock ticker v2\\frontend\\src\\components\\SelfLearningLab.jsx", "source_location": "L28"}, {"caller_nid": "selflearninglab_selflearninglab", "callee": "useState", "source_file": "E:\\Website\\Stock Analysis\\stock ticker v2\\frontend\\src\\components\\SelfLearningLab.jsx", "source_location": "L29"}, {"caller_nid": "selflearninglab_selflearninglab", "callee": "useState", "source_file": "E:\\Website\\Stock Analysis\\stock ticker v2\\frontend\\src\\components\\SelfLearningLab.jsx", "source_location": "L30"}, {"caller_nid": "selflearninglab_selflearninglab", "callee": "useState", "source_file": "E:\\Website\\Stock Analysis\\stock ticker v2\\frontend\\src\\components\\SelfLearningLab.jsx", "source_location": "L31"}, {"caller_nid": "selflearninglab_selflearninglab", "callee": "useState", "source_file": "E:\\Website\\Stock Analysis\\stock ticker v2\\frontend\\src\\components\\SelfLearningLab.jsx", "source_location": "L32"}, {"caller_nid": "selflearninglab_selflearninglab", "callee": "useState", "source_file": "E:\\Website\\Stock Analysis\\stock ticker v2\\frontend\\src\\components\\SelfLearningLab.jsx", "source_location": "L33"}, {"caller_nid": "selflearninglab_selflearninglab", "callee": "useState", "source_file": "E:\\Website\\Stock Analysis\\stock ticker v2\\frontend\\src\\components\\SelfLearningLab.jsx", "source_location": "L34"}, {"caller_nid": "selflearninglab_selflearninglab", "callee": "useState", "source_file": "E:\\Website\\Stock Analysis\\stock ticker v2\\frontend\\src\\components\\SelfLearningLab.jsx", "source_location": "L35"}, {"caller_nid": "selflearninglab_selflearninglab", "callee": "useState", "source_file": "E:\\Website\\Stock Analysis\\stock ticker v2\\frontend\\src\\components\\SelfLearningLab.jsx", "source_location": "L36"}, {"caller_nid": "selflearninglab_selflearninglab", "callee": "useEffect", "source_file": "E:\\Website\\Stock Analysis\\stock ticker v2\\frontend\\src\\components\\SelfLearningLab.jsx", "source_location": "L65"}, {"caller_nid": "selflearninglab_selflearninglab", "callee": "min", "source_file": "E:\\Website\\Stock Analysis\\stock ticker v2\\frontend\\src\\components\\SelfLearningLab.jsx", "source_location": "L90"}, {"caller_nid": "selflearninglab_selflearninglab", "callee": "round", "source_file": "E:\\Website\\Stock Analysis\\stock ticker v2\\frontend\\src\\components\\SelfLearningLab.jsx", "source_location": "L90"}, {"caller_nid": "selflearninglab_selflearninglab", "callee": "map", "source_file": "E:\\Website\\Stock Analysis\\stock ticker v2\\frontend\\src\\components\\SelfLearningLab.jsx", "source_location": "L181"}, {"caller_nid": "selflearninglab_selflearninglab", "callee": "filter", "source_file": "E:\\Website\\Stock Analysis\\stock ticker v2\\frontend\\src\\components\\SelfLearningLab.jsx", "source_location": "L346"}, {"caller_nid": "selflearninglab_selflearninglab", "callee": "map", "source_file": "E:\\Website\\Stock Analysis\\stock ticker v2\\frontend\\src\\components\\SelfLearningLab.jsx", "source_location": "L372"}, {"caller_nid": "selflearninglab_selflearninglab", "callee": "map", "source_file": "E:\\Website\\Stock Analysis\\stock ticker v2\\frontend\\src\\components\\SelfLearningLab.jsx", "source_location": "L454"}, {"caller_nid": "selflearninglab_selflearninglab", "callee": "map", "source_file": "E:\\Website\\Stock Analysis\\stock ticker v2\\frontend\\src\\components\\SelfLearningLab.jsx", "source_location": "L556"}, {"caller_nid": "selflearninglab_selflearninglab", "callee": "slice", "source_file": "E:\\Website\\Stock Analysis\\stock ticker v2\\frontend\\src\\components\\SelfLearningLab.jsx", "source_location": "L645"}, {"caller_nid": "selflearninglab_selflearninglab", "callee": "String", "source_file": "E:\\Website\\Stock Analysis\\stock ticker v2\\frontend\\src\\components\\SelfLearningLab.jsx", "source_location": "L645"}, {"caller_nid": "selflearninglab_selflearninglab", "callee": "filter", "source_file": "E:\\Website\\Stock Analysis\\stock ticker v2\\frontend\\src\\components\\SelfLearningLab.jsx", "source_location": "L670"}, {"caller_nid": "selflearninglab_selflearninglab", "callee": "slice", "source_file": "E:\\Website\\Stock Analysis\\stock ticker v2\\frontend\\src\\components\\SelfLearningLab.jsx", "source_location": "L707"}, {"caller_nid": "selflearninglab_selflearninglab", "callee": "String", "source_file": "E:\\Website\\Stock Analysis\\stock ticker v2\\frontend\\src\\components\\SelfLearningLab.jsx", "source_location": "L707"}, {"caller_nid": "selflearninglab_selflearninglab", "callee": "toFixed", "source_file": "E:\\Website\\Stock Analysis\\stock ticker v2\\frontend\\src\\components\\SelfLearningLab.jsx", "source_location": "L729"}]}